README
setup.py
django_mimemail.egg-info/PKG-INFO
django_mimemail.egg-info/SOURCES.txt
django_mimemail.egg-info/dependency_links.txt
django_mimemail.egg-info/requires.txt
django_mimemail.egg-info/top_level.txt
mimemail/__init__.py
mimemail/mail.py