Metadata-Version: 1.0
Name: django-mimemail
Version: 0.1
Summary: Helper library for sending mime-mails with inline pictures.
Home-page: http://bitbucket.org/madssj/django-mimemail/
Author: Mads Sulau Joergensen
Author-email: mads@sulau.dk
License: BSD
Platform: UNKNOWN
